{
  "time" : {
    "start" : 1508403961794,
    "stop" : 1508404008971,
    "duration" : 47177
  },
  "testSuites" : [ {
    "uid" : "fc5bb5a2d063d46e",
    "name" : "dz.WebDriverTest",
    "title" : "Web driver test",
    "time" : {
      "start" : 1508403961794,
      "stop" : 1508404008971,
      "duration" : 47177
    },
    "statistic" : {
      "total" : 1,
      "passed" : 1,
      "pending" : 0,
      "canceled" : 0,
      "failed" : 0,
      "broken" : 0
    },
    "description" : null,
    "testCases" : [ {
      "uid" : "7d1327fad1c95897",
      "name" : "webDriver",
      "title" : "Web driver",
      "time" : {
        "start" : 1508403961794,
        "stop" : 1508404008971,
        "duration" : 47177
      },
      "severity" : "NORMAL",
      "status" : "PASSED"
    } ]
  } ]
}